pretty_text_test/__init__.py
pretty_text_test/pretty.py
pretty_text_test-0.1.0.dist-info/WHEEL
pretty_text_test-0.1.0.dist-info/METADATA
pretty_text_test-0.1.0.dist-info/RECORD
